qiita_sync/__init__.py
qiita_sync/qiita_sync.py
qiita_sync-1.4.4.dist-info/entry_points.txt
qiita_sync-1.4.4.dist-info/LICENSE
qiita_sync-1.4.4.dist-info/WHEEL
qiita_sync-1.4.4.dist-info/METADATA
qiita_sync-1.4.4.dist-info/RECORD
