Metadata-Version: 2.1
Name: qiita-sync
Version: 1.4.4
Summary: Synchronize GitHub with Qiita
Home-page: https://github.com/ryokat3/qiita-sync
Author: Ryoji Kato
Author-email: ryokat3@gmail.com
Requires-Python: >=3.7,<4.0
Classifier: Programming Language :: Python :: 3
Classifier: Programming Language :: Python :: 3.10
Classifier: Programming Language :: Python :: 3.7
Classifier: Programming Language :: Python :: 3.8
Classifier: Programming Language :: Python :: 3.9
